redis_push/__init__.py
redis_push/logger.py
redis_push/model/influxdb.py
redis_push/model/slack.py
redis_push/redis.py
redis_push-0.0.3.dist-info/WHEEL
redis_push-0.0.3.dist-info/METADATA
redis_push-0.0.3.dist-info/RECORD
